whisper/__init__.py
whisper/chains.py
whisper/logging.py
whisper/mkdocs_typer.py
whisper/settings.py
whisper/cli/ask.py
whisper/cli/config.py
whisper/cli/custom_typer.py
just_whisper-0.1.6.dist-info/METADATA
just_whisper-0.1.6.dist-info/WHEEL
just_whisper-0.1.6.dist-info/entry_points.txt
just_whisper-0.1.6.dist-info/RECORD
