Metadata-Version: 2.3
Name: just-whisper
Version: 0.1.6
Summary: Whisper 🤫 sweet nothin's to your favorite LLM.
Author-email: Myg0t <myg0tm3dia@gmail.com>
Requires-Python: >=3.10
Requires-Dist: clipboard>=0.0.4
Requires-Dist: gpt4all>=2.8.2
Requires-Dist: langchain-anthropic>=0.2.1
Requires-Dist: langchain-community>=0.3.1
Requires-Dist: langchain-core>=0.3.6
Requires-Dist: langchain-fireworks>=0.2.0
Requires-Dist: langchain-mistralai>=0.2.0
Requires-Dist: langchain-openai>=0.2.1
Requires-Dist: langchain>=0.3.1
Requires-Dist: pydantic-settings>=2.5.2
Requires-Dist: pydantic>=2.9.2
Requires-Dist: rich>=13.8.1
Requires-Dist: toml>=0.10.2
Requires-Dist: typer>=0.12.5
Provides-Extra: all
Requires-Dist: gpt4all>=2.8.2; extra == 'all'
Requires-Dist: langchain-anthropic>=0.2.1; extra == 'all'
Requires-Dist: langchain-fireworks>=0.2.0; extra == 'all'
Requires-Dist: langchain-mistralai>=0.2.0; extra == 'all'
Requires-Dist: langchain-openai>=0.2.1; extra == 'all'
Provides-Extra: anthropic
Requires-Dist: langchain-anthropic>=0.2.1; extra == 'anthropic'
Provides-Extra: fireworks
Requires-Dist: langchain-fireworks>=0.2.0; extra == 'fireworks'
Provides-Extra: gpt4all
Requires-Dist: gpt4all>=2.8.2; extra == 'gpt4all'
Provides-Extra: mistral
Requires-Dist: langchain-mistralai>=0.2.0; extra == 'mistral'
Provides-Extra: openai
Requires-Dist: langchain-openai>=0.2.1; extra == 'openai'
